fds/__init__.py
fds/sdk/__init__.py
fds/sdk/QuotesAPIforDigitalPortals/__init__.py
fds/sdk/QuotesAPIforDigitalPortals/api_client.py
fds/sdk/QuotesAPIforDigitalPortals/configuration.py
fds/sdk/QuotesAPIforDigitalPortals/exceptions.py
fds/sdk/QuotesAPIforDigitalPortals/model_utils.py
fds/sdk/QuotesAPIforDigitalPortals/rest.py
fds/sdk/QuotesAPIforDigitalPortals/api/__init__.py
fds/sdk/QuotesAPIforDigitalPortals/api/basic_api.py
fds/sdk/QuotesAPIforDigitalPortals/api/category_api.py
fds/sdk/QuotesAPIforDigitalPortals/api/instrument_api.py
fds/sdk/QuotesAPIforDigitalPortals/api/notation_api.py
fds/sdk/QuotesAPIforDigitalPortals/api/prices_api.py
fds/sdk/QuotesAPIforDigitalPortals/apis/__init__.py
fds/sdk/QuotesAPIforDigitalPortals/model/__init__.py
fds/sdk/QuotesAPIforDigitalPortals/model/attributes_member.py
fds/sdk/QuotesAPIforDigitalPortals/model/cursor_based_pagination_output_object.py
fds/sdk/QuotesAPIforDigitalPortals/model/cursor_based_pagination_output_object_without_total.py
fds/sdk/QuotesAPIforDigitalPortals/model/error_meta_object.py
fds/sdk/QuotesAPIforDigitalPortals/model/error_object.py
fds/sdk/QuotesAPIforDigitalPortals/model/inline_response200.py
fds/sdk/QuotesAPIforDigitalPortals/model/inline_response2001.py
fds/sdk/QuotesAPIforDigitalPortals/model/inline_response20010.py
fds/sdk/QuotesAPIforDigitalPortals/model/inline_response20010_data.py
fds/sdk/QuotesAPIforDigitalPortals/model/inline_response20011.py
fds/sdk/QuotesAPIforDigitalPortals/model/inline_response20011_data.py
fds/sdk/QuotesAPIforDigitalPortals/model/inline_response20012.py
fds/sdk/QuotesAPIforDigitalPortals/model/inline_response20012_data.py
fds/sdk/QuotesAPIforDigitalPortals/model/inline_response20013.py
fds/sdk/QuotesAPIforDigitalPortals/model/inline_response20013_data.py
fds/sdk/QuotesAPIforDigitalPortals/model/inline_response20013_kind.py
fds/sdk/QuotesAPIforDigitalPortals/model/inline_response20014.py
fds/sdk/QuotesAPIforDigitalPortals/model/inline_response20014_data.py
fds.sdk.QuotesAPIforDigitalPortals-0.11.1.dist-info/LICENSE
fds.sdk.QuotesAPIforDigitalPortals-0.11.1.dist-info/METADATA
fds.sdk.QuotesAPIforDigitalPortals-0.11.1.dist-info/WHEEL
fds.sdk.QuotesAPIforDigitalPortals-0.11.1.dist-info/top_level.txt
fds.sdk.QuotesAPIforDigitalPortals-0.11.1.dist-info/RECORD
